sellerlegend_api/__init__.py
sellerlegend_api/auth.py
sellerlegend_api/base.py
sellerlegend_api/client.py
sellerlegend_api/exceptions.py
sellerlegend_api/py.typed
sellerlegend_api/validators.py
sellerlegend_api/resources/__init__.py
sellerlegend_api/resources/connections.py
sellerlegend_api/resources/costs.py
sellerlegend_api/resources/inventory.py
sellerlegend_api/resources/notifications.py
sellerlegend_api/resources/reports.py
sellerlegend_api/resources/sales.py
sellerlegend_api/resources/supply_chain.py
sellerlegend_api/resources/user.py
sellerlegend_api/resources/warehouse.py
sellerlegend_api-1.0.3.dist-info/licenses/LICENSE
sellerlegend_api-1.0.3.dist-info/METADATA
sellerlegend_api-1.0.3.dist-info/WHEEL
sellerlegend_api-1.0.3.dist-info/top_level.txt
sellerlegend_api-1.0.3.dist-info/RECORD
