Metadata-Version: 2.4
Name: sellerlegend-api
Version: 1.0.3
Summary: Official Python SDK for the SellerLegend API
Home-page: https://github.com/sellerlegend/sellerlegend_api_py
Author: SellerLegend
Author-email: SellerLegend <support@sellerlegend.com>
Maintainer-email: SellerLegend <support@sellerlegend.com>
License: MIT License
Project-URL: Homepage, https://github.com/sellerlegend/sellerlegend_api_py
Project-URL: Documentation, https://dashboard.sellerlegend.com/api-docs/index.html
Project-URL: Repository, https://github.com/sellerlegend/sellerlegend_api_py
Project-URL: Issues, https://github.com/sellerlegend/sellerlegend_api_py/issues
Project-URL: Changelog, https://github.com/sellerlegend/sellerlegend_api_py/blob/main/CHANGELOG.md
Keywords: sellerlegend,api,amazon,seller,ecommerce,analytics,amazon-seller,marketplace,fba,seller-central
Classifier: Development Status :: 5 - Production/Stable
Classifier: Intended Audience :: Developers
Classifier: License :: OSI Approved :: MIT License
Classifier: Operating System :: OS Independent
Classifier: Programming Language :: Python :: 3
Classifier: Programming Language :: Python :: 3.8
Classifier: Programming Language :: Python :: 3.9
Classifier: Programming Language :: Python :: 3.10
Classifier: Programming Language :: Python :: 3.11
Classifier: Programming Language :: Python :: 3.12
Classifier: Topic :: Software Development :: Libraries :: Python Modules
Classifier: Topic :: Internet :: WWW/HTTP :: Dynamic Content
Classifier: Topic :: Office/Business :: Financial
Requires-Python: >=3.8
License-File: LICENSE
Requires-Dist: requests>=2.31.0
Requires-Dist: requests-oauthlib>=1.3.1
Provides-Extra: dev
Requires-Dist: pytest>=8.0.0; extra == "dev"
Requires-Dist: pytest-mock>=3.12.0; extra == "dev"
Requires-Dist: pytest-cov>=4.1.0; extra == "dev"
Requires-Dist: black>=23.0.0; extra == "dev"
Requires-Dist: flake8>=6.0.0; extra == "dev"
Requires-Dist: mypy>=1.5.0; extra == "dev"
Requires-Dist: types-requests>=2.31.0; extra == "dev"
Provides-Extra: test
Requires-Dist: pytest>=8.0.0; extra == "test"
Requires-Dist: pytest-mock>=3.12.0; extra == "test"
Requires-Dist: pytest-cov>=4.1.0; extra == "test"
Provides-Extra: docs
Requires-Dist: sphinx>=7.0.0; extra == "docs"
Requires-Dist: sphinx-rtd-theme>=1.3.0; extra == "docs"
Dynamic: author
Dynamic: home-page
Dynamic: license-file
Dynamic: requires-python
